README.md
setup.cfg
setup.py
django_genie/__init__.py
django_genie/code_generator.py
django_genie/models.py
django_genie.egg-info/PKG-INFO
django_genie.egg-info/SOURCES.txt
django_genie.egg-info/dependency_links.txt
django_genie.egg-info/not-zip-safe
django_genie.egg-info/requires.txt
django_genie.egg-info/top_level.txt
django_genie/management/__init__.py
django_genie/management/commands/__init__.py
django_genie/management/commands/code_generator.py
django_genie/templates/__init__.py
django_genie/templates/admin.py
django_genie/templates/routers.py
django_genie/templates/serializers.py
django_genie/templates/urls.py
django_genie/templates/views.py
django_genie/templates/viewsets.py
django_genie/templatetags/__init__.py
django_genie/templatetags/code_generator_tags.py