Metadata-Version: 1.1
Name: django-genie
Version: 0.1.1
Summary: Generate code from Django for faster development
Home-page: https://github.com/minelytics/django-genie/
Author: Minelytics Technologies
Author-email: dev@minelytics.in
License: UNKNOWN
Download-URL: https://github.com/minelytics/django-genie/archive/master.zip
Keywords: django-genie
Platform: linux
Classifier: License :: OSI Approved :: MIT License
Classifier: Programming Language :: Python :: 3.5
Classifier: Programming Language :: Python :: 3.8
Classifier: Programming Language :: Python :: 3.7
Classifier: Programming Language :: Python :: 3 :: Only
Classifier: Programming Language :: Python :: 3.6
Classifier: Operating System :: POSIX
Classifier: Operating System :: POSIX :: Linux
Classifier: Natural Language :: English
Classifier: Development Status :: 3 - Alpha
Provides: django_genie
